{
  "avisos": [
    {
      "texto": "Ceia - 13/Jul - 09h00",
      "imagem": "data/avisos/aCEIA.png",
      "linkAgenda": "",
      "executaEm": "2025-07-13"
    },
    {
      "texto": "Atletas de Cristo - 11/Ago - 20h00",
      "imagem": "data/avisos/aATL.png",
      "linkAgenda": "",
      "executaEm": "2025-08-11"
    },
    {
      "texto": "Cantina - 31/Ago - ",
      "imagem": "data/avisos/aCANTINA.png",
      "linkAgenda": "",
      "executaEm": "2025-08-30"
    },
    {
      "texto": "Bazar IBBV - 06/Set - 09h00 às 13h00",
      "imagem": "data/avisos/aBAZAR.png",
      "linkAgenda": "",
      "executaEm": "2025-09-06"
    },
    {
      "texto": "Café com a Palavra - 07/Set - 09h00",
      "imagem": "data/avisos/aCAF.png",
      "linkAgenda": "",
      "executaEm": "2025-09-07"
    },
    {
      "texto": "Reunião de Homens - 13/Set 19h30",
      "imagem": "data/avisos/aUMM.png",
      "linkAgenda": "",
      "executaEm": "2025-09-13"
    },
    {
      "texto": "Reunião de Mulheres - 13/Set 19h30",
      "imagem": "data/avisos/aMCM.png",
      "linkAgenda": "",
      "executaEm": "2025-09-13"
    },
    {
      "texto": "Reunião de Jovens - 14/Set - 10h45",
      "imagem": "data/avisos/aUJB.png",
      "linkAgenda": "",
      "executaEm": "2025-09-14"
    },
        {
      "texto": "Culto de Quarta-feira transferido para Terça-Feira, dia 16/09!!",
      "imagem": "",
      "linkAgenda": "",
      "executaEm": "2025-09-16"
    },
    {
      "texto": "Aniversário da AIBAPP - Associação das Igrejas do Planalto Paulista - Nova Canaã - 20/09 - 19h30",
      "imagem": "",
      "linkAgenda": "",
      "executaEm": "2025-09-20"
    },
    {
      "texto": "Aniversário PIB São Carlos - 27/Set",
      "imagem": "data/avisos/aPIBSC.png",
      "linkAgenda": "",
      "executaEm": "2025-09-27"
    }
  ]
}
