[
  {
    "ministerio": "Recepção",
    "escalados": [
      {
        "dia": "06/07/2025",
        "nome": "Joselito (Dé)"
      },
      {
        "dia": "13/07/2025",
        "nome": "Flavio"
      },
      {
        "dia": "20/07/2025",
        "nome": "Zane"
      },
      {
        "dia": "27/07/2025",
        "nome": "João"
      }
    ]
  },
  {
    "ministerio": "Culto Kids",
    "escalados": [
      {
        "dia": "06/07/2025",
        "nome": "Jeferson"
      },
      {
        "dia": "13/07/2025",
        "nome": "Monica"
      },
      {
        "dia": "20/07/2025",
        "nome": "Lane"
      },
      {
        "dia": "27/07/2025",
        "nome": "Rose"
      }
    ]
  },
  {
    "ministerio": "Culto de Quarta-Feira",
    "escalados": [
      {
        "dia": "02/07/2025",
        "nome": "Renato"
      },
      {
        "dia": "09/07/2025",
        "nome": "Shirley"
      },
      {
        "dia": "16/07/2025",
        "nome": "Monica"
      },
      {
        "dia": "23/07/2025",
        "nome": "Railda"
      },
            {
        "dia": "30/07/2025",
        "nome": "Leo"
      }
    ]
  },
  {
    "ministerio": "Cantina",
    "escalados": [
      {
        "dia": "13/07/2025",
        "nome": "Iromar/ Daiane/ Helem"
      }
    ]
  }
]
